tensor_build/__init__.py
tensor_build/codegen.py
tensor_build/blocks/__init__.py
tensor_build/blocks/activation_block.py
tensor_build/blocks/blocks.py
tensor_build/blocks/compile_block.py
tensor_build/blocks/conv_2d_block.py
tensor_build/blocks/dense_block.py
tensor_build/blocks/dropout_block.py
tensor_build/blocks/pooling_block.py
tensor_build-1.2.0.dist-info/METADATA
tensor_build-1.2.0.dist-info/WHEEL
tensor_build-1.2.0.dist-info/top_level.txt
tensor_build-1.2.0.dist-info/RECORD
