Metadata-Version: 2.1
Name: tensor_build
Version: 1.2.0
Summary: A block-based framework for TensorFlow
Home-page: https://github.com/stony-su/starterhacks
Author: Darren, Eddie, Kahan, Richard
Requires-Dist: tensorflow >=2.0
